models/__init__.py
models/airline.py
models/airport.py
models/flight_segment.py
models/flight_set.py
pySkyscanner/__init__.py
pySkyscanner/pyskyscanner.py
pySkyscanner/docs/__init__.py
pySkyscanner/docs/sample_query.py
pySkyscanner/docs/secrets.py
pySkyscanner-1.0.1.dist-info/DESCRIPTION.rst
pySkyscanner-1.0.1.dist-info/METADATA
pySkyscanner-1.0.1.dist-info/RECORD
pySkyscanner-1.0.1.dist-info/WHEEL
pySkyscanner-1.0.1.dist-info/metadata.json
pySkyscanner-1.0.1.dist-info/top_level.txt
