Metadata-Version: 2.0
Name: pySkyscanner
Version: 1.0.1
Summary: A basic wrapper for the Python Realtime Flight Price API
Home-page: https://github.com/nickles-lee/PySkyscanner
Author: Nick Lee
Author-email: developer@nickle.es
License: MIT
Keywords: skyscanner flights wrapper rest api library
Platform: UNKNOWN
Classifier: Development Status :: 4 - Beta
Classifier: Intended Audience :: Developers
Classifier: Topic :: Internet :: WWW/HTTP :: Indexing/Search
Classifier: License :: OSI Approved :: MIT License
Classifier: Programming Language :: Python :: 2
Classifier: Programming Language :: Python :: 2.7
Requires-Dist: requests
Provides-Extra: dev
Requires-Dist: check-manifest; extra == 'dev'
Provides-Extra: test
Requires-Dist: coverage; extra == 'test'
Requires-Dist: pytest; extra == 'test'
